pygifconvt0001/Own_Package_Making_sample.py
pygifconvt0001/__init__.py
pygifconvt0001/converter.py
pygifconvt0001-1.0.6.dist-info/LICENSE
pygifconvt0001-1.0.6.dist-info/METADATA
pygifconvt0001-1.0.6.dist-info/WHEEL
pygifconvt0001-1.0.6.dist-info/top_level.txt
pygifconvt0001-1.0.6.dist-info/RECORD
